bestFit/__init__.py
bestFit/main.py
bestFit-0.3.dist-info/LICENCE.rst
bestFit-0.3.dist-info/METADATA
bestFit-0.3.dist-info/WHEEL
bestFit-0.3.dist-info/top_level.txt
bestFit-0.3.dist-info/RECORD
