Metadata-Version: 2.1
Name: bestFit
Version: 0.3
Summary: A package for plotting best fit lines.
Home-page: UNKNOWN
Author: SebassNoob
Author-email: sebastian.ong@hotmail.com
License: MIT
Platform: UNKNOWN
Requires-Python: >=3.6
License-File: LICENCE.rst
Requires-Dist: numpy
Requires-Dist: matplotlib
